LICENSE
README.md
setup.py
Pointer/Pointer.py
Pointer/__init__.py
PyPointer.egg-info/PKG-INFO
PyPointer.egg-info/SOURCES.txt
PyPointer.egg-info/dependency_links.txt
PyPointer.egg-info/top_level.txt
test/test.py