Metadata-Version: 2.1
Name: PyPointer
Version: 1.0.0
Summary: A pointer to python
Home-page: https://github.com/0gl20shk0sbt36/Pointer/tree/pypi
Author: 0gl20shk0sbt36
Author-email: 3503973883@qq.com
License: MIT License
Platform: UNKNOWN
Classifier: Programming Language :: Python :: 3
Classifier: License :: OSI Approved :: MIT License
Classifier: Development Status :: 5 - Production/Stable
Classifier: Intended Audience :: Developers
Classifier: Operating System :: OS Independent
License-File: LICENSE
